etherweb3/__init__.py
etherweb3/constants.py
etherweb3/datastructures.py
etherweb3/exceptions.py
etherweb3/geth.py
etherweb3/logs.py
etherweb3/main.py
etherweb3/manager.py
etherweb3/meth.py
etherweb3/method.py
etherweb3/module.py
etherweb3/net.py
etherweb3/testing.py
etherweb3/tracing.py
etherweb3/types.py
etherweb3/_utils/__init__.py
etherweb3/_utils/abi.py
etherweb3/_utils/abi_element_identifiers.py
etherweb3/_utils/async_caching.py
etherweb3/_utils/async_transactions.py
etherweb3/_utils/batching.py
etherweb3/_utils/blocks.py
etherweb3/_utils/contracts.py
etherweb3/_utils/datatypes.py
etherweb3/_utils/decorators.py
etherweb3/_utils/empty.py
etherweb3/_utils/encoding.py
etherweb3/_utils/ens.py
etherweb3/_utils/error_formatters_utils.py
etherweb3/_utils/events.py
etherweb3/_utils/fee_utils.py
etherweb3/_utils/filters.py
etherweb3/_utils/formatters.py
etherweb3/_utils/http.py
etherweb3/_utils/http_session_manager.py
etherweb3/_utils/hypothesis.py
etherweb3/_utils/math.py
etherweb3/_utils/method_formatters.py
etherweb3/_utils/module.py
etherweb3/_utils/normalizers.py
etherweb3/_utils/rpc_abi.py
etherweb3/_utils/threads.py
etherweb3/_utils/transactions.py
etherweb3/_utils/type_conversion.py
etherweb3/_utils/utility_methods.py
etherweb3/_utils/validation.py
etherweb3/_utils/windows.py
etherweb3/_utils/caching/__init__.py
etherweb3/_utils/caching/caching_utils.py
etherweb3/_utils/caching/request_caching_validation.py
etherweb3/_utils/compat/__init__.py
etherweb3/_utils/contract_sources/__init__.py
etherweb3/_utils/contract_sources/compile_contracts.py
etherweb3/_utils/contract_sources/contract_data/__init__.py
etherweb3/_utils/contract_sources/contract_data/_custom_contract_data.py
etherweb3/_utils/contract_sources/contract_data/ambiguous_function_contract.py
etherweb3/_utils/contract_sources/contract_data/arrays_contract.py
etherweb3/_utils/contract_sources/contract_data/bytes_contracts.py
etherweb3/_utils/contract_sources/contract_data/constructor_contracts.py
etherweb3-0.4.2.dist-info/METADATA
etherweb3-0.4.2.dist-info/WHEEL
etherweb3-0.4.2.dist-info/top_level.txt
etherweb3-0.4.2.dist-info/RECORD
