Metadata-Version: 2.1
Name: etherweb3
Version: 0.4.2
Summary: Ether Web3 JS
